agateexcel/__init__.py
agateexcel/table_xls.py
agateexcel/table_xlsx.py
agate_excel-0.4.1.dist-info/AUTHORS.rst
agate_excel-0.4.1.dist-info/COPYING
agate_excel-0.4.1.dist-info/METADATA
agate_excel-0.4.1.dist-info/WHEEL
agate_excel-0.4.1.dist-info/top_level.txt
agate_excel-0.4.1.dist-info/RECORD
